LICENSE
README.md
setup.py
local_llm_finetune/__init__.py
local_llm_finetune/data_prep.py
local_llm_finetune/modelling.py
local_llm_finetune.egg-info/PKG-INFO
local_llm_finetune.egg-info/SOURCES.txt
local_llm_finetune.egg-info/dependency_links.txt
local_llm_finetune.egg-info/top_level.txt