Metadata-Version: 2.1
Name: local_llm_finetune
Version: 0.0.2
Summary: Fine-tune an LLM with Unsloth
Home-page: https://github.com/dhopp1/local_llm_finetune
Author: Daniel Hopp
Author-email: daniel.hopp@un.org
Classifier: Programming Language :: Python :: 3
Classifier: License :: OSI Approved :: MIT License
Classifier: Operating System :: OS Independent
Requires-Python: >=3.6
License-File: LICENSE
